consoleimages/__init__.py
consoleimages/code.py
consoleimages-1.0.0.dist-info/METADATA
consoleimages-1.0.0.dist-info/WHEEL
consoleimages-1.0.0.dist-info/top_level.txt
consoleimages-1.0.0.dist-info/RECORD
