Metadata-Version: 2.1
Name: consoleimages
Version: 1.0.0
Summary: Reads image formats and prints ascii colour text to console
Home-page: https://repl.it/@GoodCoderBadBoy/consoleimages
Author: GoodCoderBadBoy
Author-email: 
License: MIT
Platform: UNKNOWN
Classifier: License :: OSI Approved :: MIT License
Classifier: Programming Language :: Python :: 3
Classifier: Programming Language :: Python :: 3.7
